mycalculator/__init__.py
mycalculator/calculator.py
calculator_dp-0.1.3.dist-info/LICENSE
calculator_dp-0.1.3.dist-info/WHEEL
calculator_dp-0.1.3.dist-info/METADATA
calculator_dp-0.1.3.dist-info/RECORD
