Metadata-Version: 2.1
Name: calculator_dp
Version: 0.1.3
Summary: Lets do simple math
Author-email: Dainius Pakeltis <dainius.pakeltis@outlook.com>
Classifier: License :: OSI Approved :: MIT License
